watchmen_storage_mongodb/__init__.py
watchmen_storage_mongodb/codes_options.py
watchmen_storage_mongodb/data_source_mongo.py
watchmen_storage_mongodb/document_defs_helper.py
watchmen_storage_mongodb/document_defs_mongo.py
watchmen_storage_mongodb/document_mongo.py
watchmen_storage_mongodb/engine_mongo.py
watchmen_storage_mongodb/sort_build.py
watchmen_storage_mongodb/storage_mongo.py
watchmen_storage_mongodb/storage_mongo_configuration.py
watchmen_storage_mongodb/topic_document_generate.py
watchmen_storage_mongodb/where_build.py
watchmen_storage_mongodb-18.0.1.dist-info/METADATA
watchmen_storage_mongodb-18.0.1.dist-info/WHEEL
watchmen_storage_mongodb-18.0.1.dist-info/licenses/LICENSE
watchmen_storage_mongodb-18.0.1.dist-info/RECORD
